xzonn_mt_tools/__init__.py
xzonn_mt_tools/config.py
xzonn_mt_tools/helper.py
xzonn_mt_tools/actions/__init__.py
xzonn_mt_tools/actions/compare_mt.py
xzonn_mt_tools/actions/export_all_lines.py
xzonn_mt_tools/actions/split_texts.py
xzonn_mt_tools/actions/update_checked_mt.py
xzonn_mt_tools/actions/update_mt_database.py
xzonn_mt_tools/actions/update_translations.py
xzonn_mt_tools-0.1.5.dist-info/licenses/LICENSE
xzonn_mt_tools-0.1.5.dist-info/METADATA
xzonn_mt_tools-0.1.5.dist-info/WHEEL
xzonn_mt_tools-0.1.5.dist-info/top_level.txt
xzonn_mt_tools-0.1.5.dist-info/RECORD
