Metadata-Version: 2.4
Name: xzonn-mt-tools
Version: 0.1.5
Author-email: Xzonn <Xzonn@outlook.com>
License: MIT License
Requires-Python: >=3.10
License-File: LICENSE
Dynamic: license-file
